typerusx/__init__.py
typerusx/sentences.json
typerusx/typing_1.py
typerux-1.0.5.dist-info/METADATA
typerux-1.0.5.dist-info/WHEEL
typerux-1.0.5.dist-info/entry_points.txt
typerux-1.0.5.dist-info/top_level.txt
typerux-1.0.5.dist-info/RECORD
