Metadata-Version: 2.1
Name: typerux
Version: 1.0.5
Requires-Dist: curses-menu
